tetsudai/__init__.py
tetsudai/_codegen.py
tetsudai/_release.py
tetsudai/py.typed
tetsudai-2.0.0.dist-info/METADATA
tetsudai-2.0.0.dist-info/WHEEL
tetsudai-2.0.0.dist-info/RECORD
