Metadata-Version: 2.4
Name: tetsudai
Version: 2.0.0
Summary: Add your description here
Author-email: unfode <forrest.futao.wei@gmail.com>
Requires-Python: >=3.13
Requires-Dist: pyright>=1.1.402
Requires-Dist: tomli-w>=1.2.0
